calculator/Addition.py
calculator/Substraction.py
nandanisamplepackage-0.0.3.dist-info/METADATA
nandanisamplepackage-0.0.3.dist-info/WHEEL
nandanisamplepackage-0.0.3.dist-info/top_level.txt
nandanisamplepackage-0.0.3.dist-info/RECORD
