Metadata-Version: 2.1
Name: nandanisamplepackage
Version: 0.0.3
Summary: A small example package
Author-email: Nandani <nandani@example.com>
Project-URL: Homepage, https://github.com/pypa/sampleproject
Project-URL: Issues, https://github.com/pypa/sampleproject/issues
Classifier: Programming Language :: Python :: 3
Classifier: License :: OSI Approved :: MIT License
Classifier: Operating System :: OS Independent
Requires-Python: >=3.8
